{
  "minecraft:recipes/decorations/crafting_table": {
    "criteria": {
      "unlock_right_away": "2024-05-17 20:00:50 +0200"
    },
    "done": true
  },
  "minecraft:adventure/adventuring_time": {
    "criteria": {
      "minecraft:plains": "2024-05-17 20:00:52 +0200"
    },
    "done": false
  },
  "minecraft:story/root": {
    "criteria": {
      "crafting_table": "2024-05-18 10:21:24 +0200"
    },
    "done": true
  },
  "minecraft:recipes/decorations/chest": {
    "criteria": {
      "has_lots_of_items": "2024-05-18 10:21:25 +0200"
    },
    "done": true
  },
  "DataVersion": 3465
}